Workbook
Name aporte: 'PLANILHA DE INVESTIMENTO'!$D$16
Name invest_carteira: 'PLANILHA DE INVESTIMENTO'!$D$12
Name invest_periodo: 'PLANILHA DE INVESTIMENTO'!$D$17
Name patrimonio_acumulado: 'PLANILHA DE INVESTIMENTO'!$D$19
Name perfil_investidor: 'PLANILHA DE INVESTIMENTO'!$C$30
Name salario: 'PLANILHA DE INVESTIMENTO'!$D$11
Name sug_investimento: 'PLANILHA DE INVESTIMENTO'!$D$13
Name taxa_mensal: 'PLANILHA DE INVESTIMENTO'!$D$18
Name valor_perfil: 'PLANILHA DE INVESTIMENTO'!$C$31

Sheet PLANILHA DE INVESTIMENTO
B10: CONFIGURAÇÕES
B11: SALÁRIO | D11: 2000
B12: RENDIMENTO CARTEIRA | D12: 0.0089
B13: SUGESTÃO DE INVESTIMENTO (30%) | D13: =D11*30% -> 600
B15: INVESTIMENTO MENSAL
B16: Quanto investir por mês? | D16: 560
B17: Por quantos anos? | D17: 5
B18: Taxa de rendimento mensal? | D18: 0.01079
B19: Patrimônio acumulado? | D19: =FV(taxa_mensal,invest_periodo*12,aporte*-1) -> 46915.072
B20: Dividendos mensais? | D20: =patrimonio_acumulado*invest_carteira -> 417.54414
B22: CENÁRIOS | C22: RESULTADO | D22: DIVIDENDO
A23: 2 | B23: Quanto em 2 anos? | C23: =FV($D$18,$A23*12,$D$16*-1) -> 15247.471 | D23: =$C23*$D$12 -> 135.70249
A24: 5 | B24: Quanto em 5 anos? | C24: =FV($D$18,$A24*12,$D$16*-1) -> 46915.072 | D24: =$C24*$D$12 -> 417.54414
A25: 10 | B25: Quanto em 10 anos? | C25: =FV($D$18,$A25*12,$D$16*-1) -> 136239.16 | D25: =$C25*$D$12 -> 1212.5285
A26: 20 | B26: Quanto em 20 anos? | C26: =FV($D$18,$A26*12,$D$16*-1) -> 630111.1 | D26: =$C26*$D$12 -> 5607.9888
A27: 30 | B27: Quanto em 30 anos? | C27: =FV($D$18,$A27*12,$D$16*-1) -> 2420415 | D27: =$C27*$D$12 -> 21541.694
B30: PERFIL | C30: MODERADO
B31: VALOR A SER INVESTIDO NO MÊS | C31: =aporte -> 560
B34: TIPO | C34: PERCENTUAL SUGERIDO | D34: VALOR
B35: PAPEL | C35: =VLOOKUP(perfil_investidor&"-"&$B35,'TABELA TIPOS'!$A:$D,4,FALSE) -> 0.3 | D35: =valor_perfil*C35 -> 168
B36: TIJOLO | C36: =VLOOKUP(perfil_investidor&"-"&$B36,'TABELA TIPOS'!$A:$D,4,FALSE) -> 0.4 | D36: =valor_perfil*C36 -> 224
B37: HÍBRIDO | C37: =VLOOKUP(perfil_investidor&"-"&$B37,'TABELA TIPOS'!$A:$D,4,FALSE) -> 0.1 | D37: =valor_perfil*C37 -> 56
B38: FOFs | C38: =VLOOKUP(perfil_investidor&"-"&$B38,'TABELA TIPOS'!$A:$D,4,FALSE) -> 0.05 | D38: =valor_perfil*C38 -> 28
B39: DESENVOLVIMENTO | C39: =VLOOKUP(perfil_investidor&"-"&$B39,'TABELA TIPOS'!$A:$D,4,FALSE) -> 0.15 | D39: =valor_perfil*C39 -> 84
B40: HOTELARIAS | C40: =VLOOKUP(perfil_investidor&"-"&$B40,'TABELA TIPOS'!$A:$D,4,FALSE) -> 0 | D40: =valor_perfil*C40 -> 0
C41: =SUM(C35:C40) -> 1 | D41: =SUM(D35:D40) -> 560
A43: 30

Sheet TABELA TIPOS
A4: CHAVE | B4: PERFIL | C4: TIPO | D4: %
A5: =B5&"-"&C5 -> CONSERVADOR-PAPEL | B5: CONSERVADOR | C5: PAPEL | D5: 0.25 | H5: %
A6: =B6&"-"&C6 -> CONSERVADOR-TIJOLO | B6: CONSERVADOR | C6: TIJOLO | D6: 0.4 | G6: AGRESSIVO-PAPEL | H6: =VLOOKUP(G6,$A:$D,4,FALSE) -> 0.45
A7: =B7&"-"&C7 -> CONSERVADOR-HÍBRIDO | B7: CONSERVADOR | C7: HÍBRIDO | D7: 0.2
A8: =B8&"-"&C8 -> CONSERVADOR-FOFs | B8: CONSERVADOR | C8: FOFs | D8: 0.05
A9: =B9&"-"&C9 -> CONSERVADOR-DESENVOLVIMENTO | B9: CONSERVADOR | C9: DESENVOLVIMENTO | D9: 0.1
A10: =B10&"-"&C10 -> CONSERVADOR-HOTELARIAS | B10: CONSERVADOR | C10: HOTELARIAS | D10: 0
A11: =B11&"-"&C11 -> MODERADO-PAPEL | B11: MODERADO | C11: PAPEL | D11: 0.3
A12: =B12&"-"&C12 -> MODERADO-TIJOLO | B12: MODERADO | C12: TIJOLO | D12: 0.4
A13: =B13&"-"&C13 -> MODERADO-HÍBRIDO | B13: MODERADO | C13: HÍBRIDO | D13: 0.1
A14: =B14&"-"&C14 -> MODERADO-FOFs | B14: MODERADO | C14: FOFs | D14: 0.05
A15: =B15&"-"&C15 -> MODERADO-DESENVOLVIMENTO | B15: MODERADO | C15: DESENVOLVIMENTO | D15: 0.15
A16: =B16&"-"&C16 -> MODERADO-HOTELARIAS | B16: MODERADO | C16: HOTELARIAS | D16: 0
A17: =B17&"-"&C17 -> AGRESSIVO-PAPEL | B17: AGRESSIVO | C17: PAPEL | D17: 0.45
A18: =B18&"-"&C18 -> AGRESSIVO-TIJOLO | B18: AGRESSIVO | C18: TIJOLO | D18: 0.3
... A22: =B22&"-"&C22 -> AGRESSIVO-HOTELARIAS | B22: AGRESSIVO | C22: HOTELARIAS | D22: 0.07
